parse_stuff/__init__.py
parse_stuff/cli.py
parse_stuff/parse_stuff.py
parse_stuff-0.1.1.dist-info/DESCRIPTION.rst
parse_stuff-0.1.1.dist-info/METADATA
parse_stuff-0.1.1.dist-info/RECORD
parse_stuff-0.1.1.dist-info/WHEEL
parse_stuff-0.1.1.dist-info/entry_points.txt
parse_stuff-0.1.1.dist-info/metadata.json
parse_stuff-0.1.1.dist-info/top_level.txt
